{
  "dataset_inventory": {
    "train_rows": 80000,
    "train_columns": 40,
    "chief_complaints_rows": 100000,
    "patient_history_rows": 100000,
    "test_rows": 20000
  },
  "overall_metrics": {
    "accuracy": 0.8501,
    "weighted_roc_auc": 0.9697,
    "macro_f1": 0.8681,
    "weighted_f1": 0.8509,
    "weighted_precision": 0.8524,
    "weighted_recall": 0.8501,
    "low_confidence_share": 0.1193,
    "test_rows": 16000,
    "total_errors": 2399,
    "adjacent_errors": 2359,
    "dangerous_errors": 40,
    "duplicate_rows_removed": 0,
    "old_baseline_accuracy": 0.8499,
    "accuracy_delta_vs_old": 0.0002
  },
  "confidence_summary": {
    "bucket_metrics": [
      {
        "bucket": "<0.60",
        "count": 1909,
        "accuracy": 0.5411
      },
      {
        "bucket": "0.60-0.69",
        "count": 1623,
        "accuracy": 0.6445
      },
      {
        "bucket": "0.70-0.79",
        "count": 1812,
        "accuracy": 0.7445
      },
      {
        "bucket": "0.80-0.89",
        "count": 2323,
        "accuracy": 0.8618
      },
      {
        "bucket": "0.90-1.00",
        "count": 8333,
        "accuracy": 0.9806
      }
    ],
    "low_confidence_share": 0.1193
  },
  "runtime_contract_check": {
    "training_style_accuracy": 0.8501,
    "current_service_contract_accuracy": 0.8501,
    "accuracy_delta": 0.0,
    "multi_risk_mismatch_rate": 0.0
  },
  "per_class_metrics": [
    {
      "class": "1",
      "precision": 0.9385,
      "recall": 0.9472,
      "f1_score": 0.9428,
      "support": 644
    },
    {
      "class": "2",
      "precision": 0.977,
      "recall": 0.9635,
      "f1_score": 0.9702,
      "support": 2688
    },
    {
      "class": "3",
      "precision": 0.8991,
      "recall": 0.8686,
      "f1_score": 0.8836,
      "support": 5784
    },
    {
      "class": "4",
      "precision": 0.762,
      "recall": 0.7593,
      "f1_score": 0.7607,
      "support": 4604
    },
    {
      "class": "5",
      "precision": 0.7455,
      "recall": 0.825,
      "f1_score": 0.7833,
      "support": 2280
    }
  ],
  "feature_importance": [
    {
      "feature": "gcs_total",
      "importance": 0.440424
    },
    {
      "feature": "news2_score",
      "importance": 0.240464
    },
    {
      "feature": "pain_score",
      "importance": 0.086036
    },
    {
      "feature": "spo2",
      "importance": 0.037325
    },
    {
      "feature": "num_prior_ed_visits_12m",
      "importance": 0.026695
    },
    {
      "feature": "temperature_c",
      "importance": 0.01914
    },
    {
      "feature": "hypoxia_flag",
      "importance": 0.016806
    },
    {
      "feature": "mean_arterial_pressure",
      "importance": 0.016057
    },
    {
      "feature": "mental_status_triage",
      "importance": 0.01392
    },
    {
      "feature": "tachycardia_flag",
      "importance": 0.012275
    },
    {
      "feature": "respiratory_rate",
      "importance": 0.011274
    },
    {
      "feature": "multi_risk_flag",
      "importance": 0.011244
    },
    {
      "feature": "heart_rate",
      "importance": 0.009611
    },
    {
      "feature": "spo2_resp_interaction",
      "importance": 0.007266
    },
    {
      "feature": "high_fever_flag",
      "importance": 0.006301
    }
  ],
  "clinically_important_missingness": [
    {
      "feature": "systolic_bp",
      "missing_pct": 5.18
    },
    {
      "feature": "diastolic_bp",
      "missing_pct": 5.18
    },
    {
      "feature": "mean_arterial_pressure",
      "missing_pct": 5.18
    },
    {
      "feature": "pulse_pressure",
      "missing_pct": 5.18
    },
    {
      "feature": "shock_index",
      "missing_pct": 5.18
    },
    {
      "feature": "respiratory_rate",
      "missing_pct": 3.83
    },
    {
      "feature": "temperature_c",
      "missing_pct": 0.72
    }
  ],
  "model_metadata": {
    "model_family": "XGBoost",
    "source_file": "train.csv",
    "selected_feature_count": 40,
    "smote_applied": true
  }
}